risiparse/__init__.py
risiparse/html_to_pdf.py
risiparse/risiparse.py
risiparse/sites_selectors.py
risiparse/utils/__init__.py
risiparse/utils/database.py
risiparse/utils/log.py
risiparse/utils/utils.py
risiparse/utils/utils_page_downloader.py
risiparse/utils/utils_posts.py
risiparse-2.0.4.dist-info/LICENSE
risiparse-2.0.4.dist-info/METADATA
risiparse-2.0.4.dist-info/WHEEL
risiparse-2.0.4.dist-info/entry_points.txt
risiparse-2.0.4.dist-info/top_level.txt
risiparse-2.0.4.dist-info/RECORD
