Metadata-Version: 2.1
Name: risiparse
Version: 2.0.4
Summary: A script to download risitas
Home-page: https://github.com/vichelisdelapaz/risiparse
Author: Vichelis
Author-email: vichelis@prefecturedelapaz.com
License: UNKNOWN
Project-URL: Bug Tracker, https://github.com/vichelisdelapaz/risiparse/issues
Platform: UNKNOWN
Classifier: Programming Language :: Python :: 3
Classifier: License :: OSI Approved :: GNU General Public License v3 (GPLv3)
Classifier: Operating System :: OS Independent
Classifier: Intended Audience :: Developers
Classifier: Intended Audience :: End Users/Desktop
Requires-Python: >=3.6
License-File: LICENSE
Requires-Dist: requests
Requires-Dist: BeautifulSoup4
Requires-Dist: PySide6
Requires-Dist: lxml
Requires-Dist: colorama
Requires-Dist: waybackpy
Requires-Dist: PyPDF2
